torchfm/__init__.py
torchfm/layer.py
torchfm/dataset/__init__.py
torchfm/dataset/avazu.py
torchfm/dataset/criteo.py
torchfm/dataset/movielens.py
torchfm/model/__init__.py
torchfm/model/afi.py
torchfm/model/afm.py
torchfm/model/dcn.py
torchfm/model/dfm.py
torchfm/model/ffm.py
torchfm/model/fm.py
torchfm/model/fnfm.py
torchfm/model/fnn.py
torchfm/model/lr.py
torchfm/model/nfm.py
torchfm/model/pnn.py
torchfm/model/wd.py
torchfm/model/xdfm.py
torchfm-0.2.dist-info/LICENSE
torchfm-0.2.dist-info/METADATA
torchfm-0.2.dist-info/WHEEL
torchfm-0.2.dist-info/top_level.txt
torchfm-0.2.dist-info/RECORD
