Metadata-Version: 2.1
Name: torchfm
Version: 0.2
Summary: PyTorch implementation of Factorization Machine Models
Home-page: https://github.com/rixwew/torchfm
Author: rixwew
Author-email: rixwew@gmail.com
License: UNKNOWN
Platform: UNKNOWN
